{
    "link": "https://pusiknas.polri.go.id/laka_lantas",
    "domain": "pusiknas.polri.go.id",
    "tag": [
        "pusiknas.polri.go.id",
        "laka_lantas"
    ],
    "crawling_time": "2024-04-24 10:45:35",
    "crawling_time_epoch": 1713930335,
    "date": "02/27/2022",
    "data": {
        "Tipe Laka Lantas New": {
            "Di simpang, tabrakan dengan Kendaraan B yang datang dari arah kiri": 9,
            "Tabrak kendaraan belok kanan dengan kendaraan yang jalan lurus": 12,
            "Tabrakan saat menyalip dari kanan": 16,
            "Tabrakan kendaraan belok kanan dengan kendaraan yang datang dari arah berlawanan": 19,
            "Tabrakan saat menyalip": 19,
            "Di ruas jalan, pejalan kaki menyeberang dari kiri ke kanan": 21,
            "Kendaraan Out of Control keluar ke kanan jalan": 25,
            "Tabrakan depan - depan": 39,
            "Tabrakan depan - belakang": 40,
            "Kendaraan Out of Control keluar ke kiri jalan": 42
        },
        "Tipe Laka Lantas Polda New": {
            "POLDA SUMATERA BARAT": 6,
            "POLDA ACEH": 7,
            "POLDA BALI": 7,
            "POLDA SULAWESI SELATAN": 15,
            "POLDA DAERAH ISTIMEWA YOGYAKARTA": 16,
            "POLDA SUMATERA UTARA": 17,
            "POLDA METRO JAYA": 18,
            "Polda Jawa Barat": 25,
            "POLDA JAWA TENGAH": 70,
            "POLDA JAWA TIMUR": 86
        },
        "Jumlah Laka Lantas New": 355,
        "Jumlah Kerugian Material": 780975220,
        "tipe korban": {
            "Luka Berat": 34,
            "Luka Ringan": 423,
            "Meninggal Dunia": 94,
            "total": 551
        },
        "penyebab": {
            "Kendaraan": 3,
            "Jalan": 5,
            "Tidak Diketahui": 39,
            "Manusia": 308
        },
        "cuaca": {
            "Berkabut/ Berasap": 1,
            "Hujan es": 1,
            "Tidak Diketahui": 5,
            "Berawan/ Mendung": 8,
            "Hujan/ Grimis": 14,
            "Cerah": 326
        }
    }
}